utils_joecatin/__init__.py
utils_joecatin/singleton.py
utils_joecatin-0.0.1.dist-info/LICENSE
utils_joecatin-0.0.1.dist-info/WHEEL
utils_joecatin-0.0.1.dist-info/METADATA
utils_joecatin-0.0.1.dist-info/RECORD
