Metadata-Version: 2.1
Name: utils-joecatin
Version: 0.0.1
Summary: personal utility package for Python3
Home-page: https://github.com/joecatin/utils-py
License: MIT
Keywords: utils,python3
Author: joe
Author-email: catinjoe@gmail.com
Requires-Python: >=3.7,<4.0
Classifier: License :: OSI Approved :: MIT License
Classifier: Programming Language :: Python :: 3
Classifier: Programming Language :: Python :: 3.7
Classifier: Programming Language :: Python :: 3.8
Classifier: Programming Language :: Python :: 3.9
Classifier: Programming Language :: Python :: 3.10
Project-URL: Repository, https://github.com/joecatin/utils-py
